gym_demo/__init__.py
gym_demo/demo.py
gym_demo/formatting.py
gym_demo-0.2.2.dist-info/LICENSE
gym_demo-0.2.2.dist-info/METADATA
gym_demo-0.2.2.dist-info/WHEEL
gym_demo-0.2.2.dist-info/entry_points.txt
gym_demo-0.2.2.dist-info/top_level.txt
gym_demo-0.2.2.dist-info/RECORD
