Metadata-Version: 2.1
Name: gym-demo
Version: 0.2.2
Summary: Explore OpenAI Gym environments.
Home-page: https://github.com/postrational/gym-demo
Author: Michal Karzynski
Author-email: github@karzyn.com
License: UNKNOWN
Platform: UNKNOWN
Requires-Dist: setuptools
Requires-Dist: gym
Requires-Dist: docopt
Requires-Dist: colorful
